gllm_tools.cpython-311-x86_64-linux-gnu.so
gllm_tools.pyi
gllm_tools/__init__.pyi
gllm_tools/code_interpreter/__init__.pyi
gllm_tools/code_interpreter/code_interpreter/__init__.pyi
gllm_tools/code_interpreter/code_interpreter/code_interpreter.pyi
gllm_tools/code_interpreter/code_interpreter/sandbox_code_interpreter.pyi
gllm_tools/code_interpreter/code_interpreter/tools/__init__.pyi
gllm_tools/code_interpreter/code_interpreter/tools/tools.pyi
gllm_tools/code_interpreter/code_sandbox/__init__.pyi
gllm_tools/code_interpreter/code_sandbox/bedrock_agentcore_sandbox.pyi
gllm_tools/code_interpreter/code_sandbox/constants.pyi
gllm_tools/code_interpreter/code_sandbox/e2b_sandbox.pyi
gllm_tools/code_interpreter/code_sandbox/models.pyi
gllm_tools/code_interpreter/code_sandbox/pydantic_executor_sandbox.pyi
gllm_tools/code_interpreter/code_sandbox/sandbox.pyi
gllm_tools/code_interpreter/code_sandbox/utils.pyi
gllm_tools/mcp/__init__.pyi
gllm_tools/mcp/client/__init__.pyi
gllm_tools/mcp/client/client.pyi
gllm_tools/mcp/client/config.pyi
gllm_tools/mcp/client/resource.pyi
gllm_tools/mcp/client/session.pyi
gllm_tools/mcp/client/tool.pyi
gllm_tools/mcp/client/langchain/__init__.pyi
gllm_tools/mcp/client/langchain/client.pyi
gllm_tools.build/.gitignore
gllm_tools_binary-0.2.0.dist-info/METADATA
gllm_tools_binary-0.2.0.dist-info/WHEEL
gllm_tools_binary-0.2.0.dist-info/top_level.txt
gllm_tools_binary-0.2.0.dist-info/RECORD
