Metadata-Version: 2.2
Name: gllm-tools-binary
Version: 0.2.0
Summary: A library for managing tools in Gen AI applications.
Author-email: Raymond Christopher <raymond.christopher@gdplabs.id>
Requires-Python: <3.14,>=3.11
Requires-Dist: e2b-code-interpreter<3.0.0,>=2.2.0
Requires-Dist: gllm-inference-binary[anthropic,openai]<0.6.0,>=0.5.0
Requires-Dist: langchain-core<0.4.0,>=0.3.63
Requires-Dist: mcp<2.0.0,>=1.9.1
Requires-Dist: pydantic<3.0.0,>=2.9.1
Requires-Dist: urllib3<3.0.0,>=2.6.0
Requires-Dist: aioboto3<16.0.0,>=15.0.0
Requires-Dist: gllm-core-binary<0.5.0,>=0.3.0
Requires-Dist: aiohttp<4.0.0,>=3.9.0
Provides-Extra: dev
Requires-Dist: pytest<9.0.0,>=8.1.1; extra == "dev"
Requires-Dist: pre-commit<4.0.0,>=3.7.0; extra == "dev"
Requires-Dist: pytest-cov<6.0.0,>=5.0.0; extra == "dev"
Requires-Dist: pytest-asyncio<1.0.0,>=0.23.6; extra == "dev"
Requires-Dist: coverage<8.0.0,>=7.4.4; extra == "dev"
Requires-Dist: mypy<2.0.0,>=1.11.2; extra == "dev"
Requires-Dist: ruff<1.0.0,>=0.11.12; extra == "dev"
Requires-Dist: python-dotenv<2.0.0,>=1.0.0; extra == "dev"
